{
  "benchmark": "long_horizon_memory_v2",
  "config_path": "configs/phase10/dev/hard_st_benchmark_b_v2_teacher1874_refine_multiview_sinkpacketbaseline_crossattn_finalqweight_longer_lowlr.yaml",
  "method": "hard_st",
  "results_dir": "results/phase10_panel/teacher1874_crossattn_panel/seed10317",
  "summary": {
    "best_metric_name": "per_mode.delay_to_final_query.accuracy",
    "best_val_accuracy": 0.9873046875,
    "best_val_metrics": {
      "accuracy": 0.9873046875,
      "anti_exit_loss": 0.0,
      "compute": 68.9287109375,
      "control_clear_mean": 0.0,
      "control_loss": 0.0,
      "control_prob_mean": 0.9078824520111084,
      "control_set_mean": 0.2321155071258545,
      "control_state_mean": 0.37175288796424866,
      "decision_count": 68.9287109375,
      "delay_rate": 0.7265678644180298,
      "delay_retain_mean": 0.7475574612617493,
      "delay_write_loss": 0.0,
      "delay_write_mean": 0.2023216187953949,
      "delays": 67.9287109375,
      "early_exit_mass": 0.25244140625,
      "early_exit_rate": 0.25244140625,
      "examples_per_sec": 855.4207942528031,
      "examples_seen": 2048,
      "exit_age_mean": 67.9287109375,
      "exit_rate": 0.2734321355819702,
      "exit_time": 67.9287109375,
      "exits": 1.0,
      "final_query_wait_gap": 2.70556640625,
      "forward_rate": 0.0,
      "hops": 0.0,
      "loss": 0.3580302894115448,
      "mailbox_occupancy": 0.5306930541992188,
      "mailbox_peak": 0.74755859375,
      "memory_payload_loss": 0.0,
      "memory_read_entropy": 0.966197669506073,
      "memory_read_mean": 0.5107262134552002,
      "memory_write_entropy": 0.3616054058074951,
      "memory_write_mean": 0.2023216187953949,
      "oracle_route_loss": 0.0,
      "packet_age_max": 67.9287109375,
      "packet_age_mean": 33.96435546875,
      "peak_memory_mb": 111.732421875,
      "penalty_delays": 0.20378613471984863,
      "penalty_hops": 0.0,
      "penalty_ttl": 0.0,
      "per_mode": {
        "delay_to_final_query": {
          "accuracy": 0.9821251252556984,
          "anti_exit_loss": 0.0,
          "compute": 122.4975179541549,
          "control_clear_mean": 0.0,
          "control_loss": 0.0,
          "control_prob_mean": 0.9698922631757143,
          "control_set_mean": 0.21844342531490232,
          "control_state_mean": 0.4654940444580256,
          "count": 1007,
          "decision_count": 122.4975179541549,
          "delay_rate": 0.9883560395643278,
          "delay_retain_mean": 0.9999976638175525,
          "delay_write_loss": 0.0,
          "delay_write_mean": 0.012813086101698366,
          "delays": 121.4975179541549,
          "early_exit_mass": 0.0,
          "early_exit_rate": 0.0,
          "exit_age_mean": 121.4975179541549,
          "exit_rate": 0.011643954226238488,
          "exit_time": 121.4975179541549,
          "exits": 0.9999999928379721,
          "final_query_wait_gap": 5.502482689835701,
          "forward_rate": 0.0,
          "hops": 0.0,
          "loss": 0.35804297300767757,
          "mailbox_occupancy": 0.9491993590168352,
          "mailbox_peak": 0.9999999928379721,
          "memory_payload_loss": 0.0,
          "memory_read_entropy": 0.6862748590221235,
          "memory_read_mean": 0.5090016816199832,
          "memory_write_entropy": 0.13257716664195415,
          "memory_write_mean": 0.012813086101698366,
          "oracle_route_loss": 0.0,
          "packet_age_max": 121.4975179541549,
          "packet_age_mean": 60.74875897707745,
          "penalty_delays": 0.2042762672652554,
          "penalty_hops": 0.0,
          "penalty_ttl": 0.0,
          "policy_logprob": 0.0,
          "premature_exit_rate": 0.05660377404363058,
          "release_loss": 0.0,
          "release_prob_mean": 0.0,
          "route_entropy": 0.0020012558150487142,
          "route_loss": 0.2042762672652554,
          "route_match": 0.9433962280132328,
          "router_confidence": 0.9992505111310783,
          "task_loss": 0.15376670405549822,
          "transition_delay_to_delay": 0.9871399626949693,
          "transition_delay_to_exit": 0.012860066471057236,
          "transition_delay_to_forward": 0.0,
          "transition_exit_to_delay": 0.0,
          "transition_exit_to_exit": 0.0,
          "transition_exit_to_forward": 0.0,
          "transition_forward_to_delay": 0.0,
          "transition_forward_to_exit": 0.0,
          "transition_forward_to_forward": 0.0,
          "ttl_fail": 0.0,
          "wait_loss": 0.0,
          "wait_prob_mean": 0.0,
          "wait_state_mean": 0.0
        },
        "delay_to_trigger_exit": {
          "accuracy": 0.986641235933959,
          "anti_exit_loss": 0.0,
          "compute": 33.003817551008616,
          "control_clear_mean": 0.0,
          "control_loss": 0.0,
          "control_prob_mean": 0.9646742684013061,
          "control_set_mean": 0.22889510354467932,
          "control_state_mean": 0.29990146775509563,
          "count": 524,
          "decision_count": 33.003817551008616,
          "delay_rate": 0.9403366611431573,
          "delay_retain_mean": 1.0,
          "delay_write_loss": 0.0,
          "delay_write_mean": 0.05666807790834258,
          "delays": 32.003817551008616,
          "early_exit_mass": 0.0,
          "early_exit_rate": 0.0,
          "exit_age_mean": 32.003817551008616,
          "exit_rate": 0.059663360362573886,
          "exit_time": 32.003817551008616,
          "exits": 1.0,
          "final_query_wait_gap": 0.0,
          "forward_rate": 0.0,
          "hops": 0.0,
          "loss": 0.35861869901418686,
          "mailbox_occupancy": 0.2500298246172548,
          "mailbox_peak": 1.0,
          "memory_payload_loss": 0.0,
          "memory_read_entropy": 0.7220249582110471,
          "memory_read_mean": 0.5096953555600334,
          "memory_write_entropy": 0.10119712216253499,
          "memory_write_mean": 0.05666807790834258,
          "oracle_route_loss": 0.0,
          "packet_age_max": 32.003817551008616,
          "packet_age_mean": 16.001908775504308,
          "penalty_delays": 0.2036586406121727,
          "penalty_hops": 0.0,
          "penalty_ttl": 0.0,
          "policy_logprob": 0.0,
          "premature_exit_rate": 0.0,
          "release_loss": 0.0,
          "release_prob_mean": 0.0,
          "route_entropy": 1.047793239889287e-05,
          "route_loss": 0.2036586406121727,
          "route_match": 1.0,
          "router_confidence": 0.9999992558519348,
          "task_loss": 0.1549600541648519,
          "transition_delay_to_delay": 0.9235921063040959,
          "transition_delay_to_exit": 0.07640790300202051,
          "transition_delay_to_forward": 0.0,
          "transition_exit_to_delay": 0.0,
          "transition_exit_to_exit": 0.0,
          "transition_exit_to_forward": 0.0,
          "transition_forward_to_delay": 0.0,
          "transition_forward_to_exit": 0.0,
          "transition_forward_to_forward": 0.0,
          "ttl_fail": 0.0,
          "wait_loss": 0.0,
          "wait_prob_mean": 0.0,
          "wait_state_mean": 0.0
        },
        "easy_exit": {
          "accuracy": 0.9980657515719504,
          "anti_exit_loss": 0.0,
          "compute": 0.9999999936590803,
          "control_clear_mean": 0.0,
          "control_loss": 0.0,
          "control_prob_mean": 0.7295408999435675,
          "control_set_mean": 0.26200964372439356,
          "control_state_mean": 0.2619905126798084,
          "count": 517,
          "decision_count": 0.9999999936590803,
          "delay_rate": 0.0,
          "delay_retain_mean": 0.0,
          "delay_write_loss": 0.0,
          "delay_write_mean": 0.7190673478106235,
          "delays": 0.0,
          "early_exit_mass": 0.9999999936590803,
          "early_exit_rate": 0.9999999936590803,
          "exit_age_mean": 0.0,
          "exit_rate": 0.9999999936590803,
          "exit_time": 0.0,
          "exits": 0.9999999936590803,
          "final_query_wait_gap": 0.0,
          "forward_rate": 0.0,
          "hops": 0.0,
          "loss": 0.3574090972975098,
          "mailbox_occupancy": 0.0,
          "mailbox_peak": 0.0,
          "memory_payload_loss": 0.0,
          "memory_read_entropy": 1.7589035041097054,
          "memory_read_mean": 0.5151301022309168,
          "memory_write_entropy": 1.0716351485114033,
          "memory_write_mean": 0.7190673478106235,
          "oracle_route_loss": 0.0,
          "packet_age_max": 0.0,
          "packet_age_mean": 0.0,
          "penalty_delays": 0.20296068109096366,
          "penalty_hops": 0.0,
          "penalty_ttl": 0.0,
          "policy_logprob": 0.0,
          "premature_exit_rate": 0.0,
          "release_loss": 0.0,
          "release_prob_mean": 0.0,
          "route_entropy": 1.2007593832658091e-05,
          "route_loss": 0.20296068109096366,
          "route_match": 0.9999999936590803,
          "router_confidence": 0.999999146973372,
          "task_loss": 0.15444841410251373,
          "transition_delay_to_delay": 0.0,
          "transition_delay_to_exit": 0.0,
          "transition_delay_to_forward": 0.0,
          "transition_exit_to_delay": 0.0,
          "transition_exit_to_exit": 0.0,
          "transition_exit_to_forward": 0.0,
          "transition_forward_to_delay": 0.0,
          "transition_forward_to_exit": 0.0,
          "transition_forward_to_forward": 0.0,
          "ttl_fail": 0.0,
          "wait_loss": 0.0,
          "wait_prob_mean": 0.0,
          "wait_state_mean": 0.0
        }
      },
      "per_slice": {
        "distance_long": {
          "accuracy": 0.9821251252556984,
          "anti_exit_loss": 0.0,
          "compute": 122.4975179541549,
          "control_clear_mean": 0.0,
          "control_loss": 0.0,
          "control_prob_mean": 0.9698922631757143,
          "control_set_mean": 0.21844342531490232,
          "control_state_mean": 0.4654940444580256,
          "count": 1007,
          "delay_rate": 0.9883560395643278,
          "delay_retain_mean": 0.9999976638175525,
          "delay_write_mean": 0.012813086101698366,
          "delays": 121.4975179541549,
          "early_exit_rate": 0.0,
          "exit_rate": 0.011643954226238488,
          "exit_time": 121.4975179541549,
          "final_query_wait_gap": 5.502482689835701,
          "memory_read_entropy": 0.6862748590221235,
          "memory_read_mean": 0.5090016816199832,
          "memory_write_entropy": 0.13257716664195415,
          "memory_write_mean": 0.012813086101698366,
          "packet_age_mean": 60.74875897707745,
          "premature_exit_rate": 0.05660377404363058,
          "release_loss": 0.0,
          "release_prob_mean": 0.0,
          "route_entropy": 0.0020012558150487142,
          "route_match": 0.9433962280132328,
          "router_confidence": 0.9992505111310783,
          "wait_loss": 0.0,
          "wait_prob_mean": 0.0,
          "wait_state_mean": 0.0
        },
        "distance_short": {
          "accuracy": 0.9923150707161507,
          "anti_exit_loss": 0.0,
          "compute": 17.109510157912197,
          "control_clear_mean": 0.0,
          "control_loss": 0.0,
          "control_prob_mean": 0.847898111563251,
          "control_set_mean": 0.24534104518255972,
          "control_state_mean": 0.28107343993429723,
          "count": 1041,
          "delay_rate": 0.4733298766166401,
          "delay_retain_mean": 0.5033621632858152,
          "delay_write_mean": 0.38564061689101997,
          "delays": 16.109510175318356,
          "early_exit_rate": 0.4966378470204635,
          "exit_rate": 0.5266701267329005,
          "exit_time": 16.109510175318356,
          "final_query_wait_gap": 0.0,
          "memory_read_entropy": 1.2369781187471578,
          "memory_read_mean": 0.5123944481213888,
          "memory_write_entropy": 0.5831533372115906,
          "memory_write_mean": 0.38564061689101997,
          "packet_age_mean": 8.054755087659178,
          "premature_exit_rate": 0.0,
          "release_loss": 0.0,
          "release_prob_mean": 0.0,
          "route_entropy": 1.1237620277192505e-05,
          "route_match": 0.9999999930718905,
          "router_confidence": 0.9999992069891162,
          "wait_loss": 0.0,
          "wait_prob_mean": 0.0,
          "wait_state_mean": 0.0
        },
        "trigger_early": {
          "accuracy": 0.9858525663902754,
          "anti_exit_loss": 0.0,
          "compute": 63.10126520925196,
          "control_clear_mean": 0.0,
          "control_loss": 0.0,
          "control_prob_mean": 0.9001608686667277,
          "control_set_mean": 0.23361742367783503,
          "control_state_mean": 0.37401375207808685,
          "count": 1343,
          "delay_rate": 0.7053842846351334,
          "delay_retain_mean": 0.7326869430243748,
          "delay_write_mean": 0.2201789206674715,
          "delays": 62.101264749102334,
          "early_exit_rate": 0.26731198957316127,
          "exit_rate": 0.29461573815487785,
          "exit_time": 62.101264749102334,
          "final_query_wait_gap": 3.5003722997539004,
          "memory_read_entropy": 0.9896163285799374,
          "memory_read_mean": 0.5187631432724283,
          "memory_write_entropy": 0.369013280830362,
          "memory_write_mean": 0.2201789206674715,
          "packet_age_mean": 31.050632374551167,
          "premature_exit_rate": 0.03350707412470612,
          "release_loss": 0.0,
          "release_prob_mean": 0.0,
          "route_entropy": 0.0013290585990151222,
          "route_match": 0.9664929336961844,
          "router_confidence": 0.9994808215750569,
          "wait_loss": 0.0,
          "wait_prob_mean": 0.0,
          "wait_state_mean": 0.0
        },
        "trigger_mid": {
          "accuracy": 0.9900709189421741,
          "anti_exit_loss": 0.0,
          "compute": 80.02978655226687,
          "control_clear_mean": 0.0,
          "control_loss": 0.0,
          "control_prob_mean": 0.9225920274748024,
          "control_set_mean": 0.22925438356737718,
          "control_state_mean": 0.36744602960897677,
          "count": 705,
          "delay_rate": 0.7669218282327585,
          "delay_retain_mean": 0.775885231275085,
          "delay_write_mean": 0.16830408008808787,
          "delays": 79.02978655226687,
          "early_exit_rate": 0.22411347737549045,
          "exit_rate": 0.23307819319955,
          "exit_time": 79.02978655226687,
          "final_query_wait_gap": 1.1914893366766315,
          "memory_read_entropy": 0.9215861671359826,
          "memory_read_mean": 0.49541620493780636,
          "memory_write_entropy": 0.34749365736406745,
          "memory_write_mean": 0.16830408008808787,
          "packet_age_mean": 39.514893276133435,
          "premature_exit_rate": 0.01702127681503482,
          "release_loss": 0.0,
          "release_prob_mean": 0.0,
          "route_entropy": 0.0003433153497679357,
          "route_match": 0.9829787250951673,
          "router_confidence": 0.9999173031631091,
          "wait_loss": 0.0,
          "wait_prob_mean": 0.0,
          "wait_state_mean": 0.0
        }
      },
      "phase": "hard_st",
      "policy_logprob": 0.0,
      "premature_exit_rate": 0.02783203125,
      "release_loss": 0.0,
      "release_prob_mean": 0.0,
      "route_entropy": 0.0009897280251607299,
      "route_loss": 0.20378613471984863,
      "route_match": 0.97216796875,
      "router_confidence": 0.9996311068534851,
      "split": "val",
      "step": 718,
      "task_loss": 0.15424412488937378,
      "transition_delay_to_delay": 0.7216856479644775,
      "transition_delay_to_exit": 0.025872962549328804,
      "transition_delay_to_forward": 0.0,
      "transition_exit_to_delay": 0.0,
      "transition_exit_to_exit": 0.0,
      "transition_exit_to_forward": 0.0,
      "transition_forward_to_delay": 0.0,
      "transition_forward_to_exit": 0.0,
      "transition_forward_to_forward": 0.0,
      "ttl_fail": 0.0,
      "wait_loss": 0.0,
      "wait_prob_mean": 0.0,
      "wait_state_mean": 0.0,
      "wall_time_sec": 2.3941433429718018
    },
    "best_val_score": 0.9821251252556984,
    "checkpoint": "results/phase10_panel/teacher1874_crossattn_panel/seed10317/hard_st_best.pt",
    "peak_train_memory_mb": 111.732421875,
    "phase_wall_time_sec": 198.04445028305054,
    "test": {
      "accuracy": 0.9847005009651184,
      "anti_exit_loss": 0.0,
      "compute": 68.3115234375,
      "control_clear_mean": 0.0,
      "control_loss": 0.0,
      "control_prob_mean": 0.9099380373954773,
      "control_set_mean": 0.23471371829509735,
      "control_state_mean": 0.3711014688014984,
      "decision_count": 68.3115234375,
      "delay_rate": 0.7235823273658752,
      "delay_retain_mean": 0.7441398501396179,
      "delay_write_loss": 0.0,
      "delay_write_mean": 0.20372235774993896,
      "delays": 67.3115234375,
      "early_exit_mass": 0.255859375,
      "early_exit_rate": 0.255859375,
      "examples_per_sec": 850.7145322295506,
      "examples_seen": 3072,
      "exit_age_mean": 67.3115234375,
      "exit_rate": 0.27641764283180237,
      "exit_time": 67.3115234375,
      "exits": 1.0,
      "final_query_wait_gap": 2.6321613788604736,
      "forward_rate": 0.0,
      "hops": 0.0,
      "loss": 0.37230560183525085,
      "mailbox_occupancy": 0.5258712768554688,
      "mailbox_peak": 0.744140625,
      "memory_payload_loss": 0.0,
      "memory_read_entropy": 0.9685397744178772,
      "memory_read_mean": 0.5062935948371887,
      "memory_write_entropy": 0.3756467401981354,
      "memory_write_mean": 0.20372235774993896,
      "oracle_route_loss": 0.0,
      "packet_age_max": 67.3115234375,
      "packet_age_mean": 33.65576171875,
      "peak_memory_mb": 111.958984375,
      "penalty_delays": 0.2019345760345459,
      "penalty_hops": 0.0,
      "penalty_ttl": 0.0,
      "per_mode": {
        "delay_to_final_query": {
          "accuracy": 0.9759358377220796,
          "anti_exit_loss": 0.0,
          "compute": 122.59491985749433,
          "control_clear_mean": 0.0,
          "control_loss": 0.0,
          "control_prob_mean": 0.97030024525316,
          "control_set_mean": 0.2186495973803302,
          "control_state_mean": 0.46138114290919535,
          "count": 1496,
          "decision_count": 122.59491985749433,
          "delay_rate": 0.9891882718884372,
          "delay_retain_mean": 0.9999982741746035,
          "delay_write_loss": 0.0,
          "delay_write_mean": 0.012041087118525277,
          "delays": 121.59491985749433,
          "early_exit_mass": 0.0,
          "early_exit_rate": 0.0,
          "exit_age_mean": 121.59491985749433,
          "exit_rate": 0.010811744582152024,
          "exit_time": 121.59491985749433,
          "exits": 0.9999999954180921,
          "final_query_wait_gap": 5.405080186491982,
          "forward_rate": 0.0,
          "hops": 0.0,
          "loss": 0.3727294036491032,
          "mailbox_occupancy": 0.9499603113866745,
          "mailbox_peak": 0.9999999954180921,
          "memory_payload_loss": 0.0,
          "memory_read_entropy": 0.6852182160644608,
          "memory_read_mean": 0.5080086551009015,
          "memory_write_entropy": 0.13085898987072356,
          "memory_write_mean": 0.012041087118525277,
          "oracle_route_loss": 0.0,
          "packet_age_max": 121.59491985749433,
          "packet_age_mean": 60.797459928747166,
          "penalty_delays": 0.20246626594088932,
          "penalty_hops": 0.0,
          "penalty_ttl": 0.0,
          "policy_logprob": 0.0,
          "premature_exit_rate": 0.05748663124015784,
          "release_loss": 0.0,
          "release_prob_mean": 0.0,
          "route_entropy": 0.0016572489606681588,
          "route_loss": 0.20246626594088932,
          "route_match": 0.9425133767532793,
          "router_confidence": 0.9993892743944485,
          "task_loss": 0.17026313895329753,
          "transition_delay_to_delay": 0.9885590581253251,
          "transition_delay_to_exit": 0.011440945371492383,
          "transition_delay_to_forward": 0.0,
          "transition_exit_to_delay": 0.0,
          "transition_exit_to_exit": 0.0,
          "transition_exit_to_forward": 0.0,
          "transition_forward_to_delay": 0.0,
          "transition_forward_to_exit": 0.0,
          "transition_forward_to_forward": 0.0,
          "ttl_fail": 0.0,
          "wait_loss": 0.0,
          "wait_prob_mean": 0.0,
          "wait_state_mean": 0.0
        },
        "delay_to_trigger_exit": {
          "accuracy": 0.9898734144017666,
          "anti_exit_loss": 0.0,
          "compute": 32.48734180112428,
          "control_clear_mean": 0.0,
          "control_loss": 0.0,
          "control_prob_mean": 0.9644584505618373,
          "control_set_mean": 0.22905993167358107,
          "control_state_mean": 0.29976261608962773,
          "count": 790,
          "decision_count": 32.48734180112428,
          "delay_rate": 0.9405307864841027,
          "delay_retain_mean": 0.9999999953976161,
          "delay_write_loss": 0.0,
          "delay_write_mean": 0.05680546027289916,
          "delays": 31.487341805953015,
          "early_exit_mass": 0.0,
          "early_exit_rate": 0.0,
          "exit_age_mean": 31.487341805953015,
          "exit_rate": 0.05946919880335844,
          "exit_time": 31.487341805953015,
          "exits": 0.9999999953976161,
          "final_query_wait_gap": 0.0,
          "forward_rate": 0.0,
          "hops": 0.0,
          "loss": 0.37133694834347014,
          "mailbox_occupancy": 0.24599485785900793,
          "mailbox_peak": 0.9999999953976161,
          "memory_payload_loss": 0.0,
          "memory_read_entropy": 0.7191735041292407,
          "memory_read_mean": 0.5098972434484506,
          "memory_write_entropy": 0.09987821977915644,
          "memory_write_mean": 0.05680546027289916,
          "oracle_route_loss": 0.0,
          "packet_age_max": 31.487341805953015,
          "packet_age_mean": 15.743670902976508,
          "penalty_delays": 0.20159038627826714,
          "penalty_hops": 0.0,
          "penalty_ttl": 0.0,
          "policy_logprob": 0.0,
          "premature_exit_rate": 0.0,
          "release_loss": 0.0,
          "release_prob_mean": 0.0,
          "route_entropy": 9.988878390905034e-06,
          "route_loss": 0.20159038627826714,
          "route_match": 0.9999999953976161,
          "router_confidence": 0.9999992968915384,
          "task_loss": 0.16974654757901084,
          "transition_delay_to_delay": 0.9259297021582157,
          "transition_delay_to_exit": 0.0740703002655808,
          "transition_delay_to_forward": 0.0,
          "transition_exit_to_delay": 0.0,
          "transition_exit_to_exit": 0.0,
          "transition_exit_to_forward": 0.0,
          "transition_forward_to_delay": 0.0,
          "transition_forward_to_exit": 0.0,
          "transition_forward_to_forward": 0.0,
          "ttl_fail": 0.0,
          "wait_loss": 0.0,
          "wait_prob_mean": 0.0,
          "wait_state_mean": 0.0
        },
        "easy_exit": {
          "accuracy": 0.9961832144484872,
          "anti_exit_loss": 0.0,
          "compute": 1.0,
          "control_clear_mean": 0.0,
          "control_loss": 0.0,
          "control_prob_mean": 0.7402522712566774,
          "control_set_mean": 0.2709712500638938,
          "control_state_mean": 0.2709733232969546,
          "count": 786,
          "decision_count": 1.0,
          "delay_rate": 0.0,
          "delay_retain_mean": 0.0,
          "delay_write_loss": 0.0,
          "delay_write_mean": 0.7162154243344265,
          "delays": 0.0,
          "early_exit_mass": 1.0,
          "early_exit_rate": 1.0,
          "exit_age_mean": 0.0,
          "exit_rate": 1.0,
          "exit_time": 0.0,
          "exits": 1.0,
          "final_query_wait_gap": 0.0,
          "forward_rate": 0.0,
          "hops": 0.0,
          "loss": 0.37247253366705724,
          "mailbox_occupancy": 0.0,
          "mailbox_peak": 0.0,
          "memory_payload_loss": 0.0,
          "memory_read_entropy": 1.7584232546900975,
          "memory_read_mean": 0.49940735860028646,
          "memory_write_entropy": 1.1187252106557366,
          "memory_write_mean": 0.7162154243344265,
          "oracle_route_loss": 0.0,
          "packet_age_max": 0.0,
          "packet_age_mean": 0.0,
          "penalty_delays": 0.20126853445331558,
          "penalty_hops": 0.0,
          "penalty_ttl": 0.0,
          "policy_logprob": 0.0,
          "premature_exit_rate": 0.0,
          "release_loss": 0.0,
          "release_prob_mean": 0.0,
          "route_entropy": 1.247221169126165e-05,
          "route_loss": 0.20126853445331558,
          "route_match": 1.0,
          "router_confidence": 0.9999991156369372,
          "task_loss": 0.17120399362106664,
          "transition_delay_to_delay": 0.0,
          "transition_delay_to_exit": 0.0,
          "transition_delay_to_forward": 0.0,
          "transition_exit_to_delay": 0.0,
          "transition_exit_to_exit": 0.0,
          "transition_exit_to_forward": 0.0,
          "transition_forward_to_delay": 0.0,
          "transition_forward_to_exit": 0.0,
          "transition_forward_to_forward": 0.0,
          "ttl_fail": 0.0,
          "wait_loss": 0.0,
          "wait_prob_mean": 0.0,
          "wait_state_mean": 0.0
        }
      },
      "per_slice": {
        "distance_long": {
          "accuracy": 0.9759358377220796,
          "anti_exit_loss": 0.0,
          "compute": 122.59491985749433,
          "control_clear_mean": 0.0,
          "control_loss": 0.0,
          "control_prob_mean": 0.97030024525316,
          "control_set_mean": 0.2186495973803302,
          "control_state_mean": 0.46138114290919535,
          "count": 1496,
          "delay_rate": 0.9891882718884372,
          "delay_retain_mean": 0.9999982741746035,
          "delay_write_mean": 0.012041087118525277,
          "delays": 121.59491985749433,
          "early_exit_rate": 0.0,
          "exit_rate": 0.010811744582152024,
          "exit_time": 121.59491985749433,
          "final_query_wait_gap": 5.405080186491982,
          "memory_read_entropy": 0.6852182160644608,
          "memory_read_mean": 0.5080086551009015,
          "memory_write_entropy": 0.13085898987072356,
          "memory_write_mean": 0.012041087118525277,
          "packet_age_mean": 60.797459928747166,
          "premature_exit_rate": 0.05748663124015784,
          "release_loss": 0.0,
          "release_prob_mean": 0.0,
          "route_entropy": 0.0016572489606681588,
          "route_match": 0.9425133767532793,
          "router_confidence": 0.9993892743944485,
          "wait_loss": 0.0,
          "wait_prob_mean": 0.0,
          "wait_state_mean": 0.0
        },
        "distance_short": {
          "accuracy": 0.9930203096742557,
          "anti_exit_loss": 0.0,
          "compute": 16.783629476721515,
          "control_clear_mean": 0.0,
          "control_loss": 0.0,
          "control_prob_mean": 0.8526399079237492,
          "control_set_mean": 0.24996239968060238,
          "control_state_mean": 0.28540450215415303,
          "count": 1576,
          "delay_rate": 0.47145897412890103,
          "delay_retain_mean": 0.5012690382371396,
          "delay_write_mean": 0.3856736258012692,
          "delays": 15.78362939260938,
          "early_exit_rate": 0.49873097127464217,
          "exit_rate": 0.528541042757821,
          "exit_time": 15.78362939260938,
          "final_query_wait_gap": 0.0,
          "memory_read_entropy": 1.2374795179076605,
          "memory_read_mean": 0.5046656156138418,
          "memory_write_entropy": 0.6080087667264914,
          "memory_write_mean": 0.3856736258012692,
          "packet_age_mean": 7.89181469630469,
          "premature_exit_rate": 0.0,
          "release_loss": 0.0,
          "release_prob_mean": 0.0,
          "route_entropy": 1.1227394004539941e-05,
          "route_match": 0.9999999900532858,
          "router_confidence": 0.9999992036955611,
          "wait_loss": 0.0,
          "wait_prob_mean": 0.0,
          "wait_state_mean": 0.0
        },
        "trigger_early": {
          "accuracy": 0.9825372197839867,
          "anti_exit_loss": 0.0,
          "compute": 64.26861781907436,
          "control_clear_mean": 0.0,
          "control_loss": 0.0,
          "control_prob_mean": 0.9083848616742574,
          "control_set_mean": 0.235283448442656,
          "control_state_mean": 0.37636638433123837,
          "count": 1947,
          "delay_rate": 0.7163926505344491,
          "delay_retain_mean": 0.7437074424122074,
          "delay_write_mean": 0.21051976907449194,
          "delays": 63.26861749775421,
          "early_exit_rate": 0.25629173171752895,
          "exit_rate": 0.2836073465189936,
          "exit_time": 63.26861749775421,
          "final_query_wait_gap": 3.0154082807260227,
          "memory_read_entropy": 0.9763948983514253,
          "memory_read_mean": 0.5116121190507779,
          "memory_write_entropy": 0.3748866676610742,
          "memory_write_mean": 0.21051976907449194,
          "packet_age_mean": 31.634308748877103,
          "premature_exit_rate": 0.028762197699809172,
          "release_loss": 0.0,
          "release_prob_mean": 0.0,
          "route_entropy": 0.0010898109914031326,
          "route_match": 0.9712377860415086,
          "router_confidence": 0.999580713437653,
          "wait_loss": 0.0,
          "wait_prob_mean": 0.0,
          "wait_state_mean": 0.0
        },
        "trigger_mid": {
          "accuracy": 0.9884444558885362,
          "anti_exit_loss": 0.0,
          "compute": 75.30844427829318,
          "control_clear_mean": 0.0,
          "control_loss": 0.0,
          "control_prob_mean": 0.9126260011990865,
          "control_set_mean": 0.23372770596875084,
          "control_state_mean": 0.36198963734838696,
          "count": 1125,
          "delay_rate": 0.7360253171920776,
          "delay_retain_mean": 0.7448879963556926,
          "delay_write_mean": 0.1919583125114441,
          "delays": 74.30844427829318,
          "early_exit_rate": 0.2551111120780309,
          "exit_rate": 0.26397468800014917,
          "exit_time": 74.30844427829318,
          "final_query_wait_gap": 1.968888875749376,
          "memory_read_entropy": 0.9549451766543918,
          "memory_read_mean": 0.4970889960659875,
          "memory_write_entropy": 0.3769622379938761,
          "memory_write_mean": 0.1919583125114441,
          "packet_age_mean": 37.15422213914659,
          "premature_exit_rate": 0.0266666664696402,
          "release_loss": 0.0,
          "release_prob_mean": 0.0,
          "route_entropy": 0.0003334015183047288,
          "route_match": 0.973333338048723,
          "router_confidence": 0.9999123742315504,
          "wait_loss": 0.0,
          "wait_prob_mean": 0.0,
          "wait_state_mean": 0.0
        }
      },
      "phase": "hard_st",
      "policy_logprob": 0.0,
      "premature_exit_rate": 0.02799479104578495,
      "release_loss": 0.0,
      "release_prob_mean": 0.0,
      "route_entropy": 0.0008128055487759411,
      "route_loss": 0.2019345760345459,
      "route_match": 0.9720051884651184,
      "router_confidence": 0.9997022151947021,
      "split": "test",
      "step": 719,
      "task_loss": 0.17037104070186615,
      "transition_delay_to_delay": 0.7195211052894592,
      "transition_delay_to_exit": 0.02461952716112137,
      "transition_delay_to_forward": 0.0,
      "transition_exit_to_delay": 0.0,
      "transition_exit_to_exit": 0.0,
      "transition_exit_to_forward": 0.0,
      "transition_forward_to_delay": 0.0,
      "transition_forward_to_exit": 0.0,
      "transition_forward_to_forward": 0.0,
      "ttl_fail": 0.0,
      "wait_loss": 0.0,
      "wait_prob_mean": 0.0,
      "wait_state_mean": 0.0,
      "wall_time_sec": 3.611082077026367
    },
    "total_parameter_count": 1055499,
    "trainable_parameter_count": 139748,
    "trainable_parameter_names": [
      "query_readout_proj.0.weight",
      "query_readout_proj.0.bias",
      "query_readout_proj.1.weight",
      "query_readout_proj.1.bias",
      "multiview_query_proj.0.weight",
      "multiview_query_proj.0.bias",
      "multiview_query_proj.1.weight",
      "multiview_query_proj.1.bias",
      "multiview_attention.in_proj_weight",
      "multiview_attention.in_proj_bias",
      "multiview_attention.out_proj.weight",
      "multiview_attention.out_proj.bias",
      "multiview_attention_norm.weight",
      "multiview_attention_norm.bias",
      "multiview_ff.0.weight",
      "multiview_ff.0.bias",
      "multiview_ff.1.weight",
      "multiview_ff.1.bias",
      "multiview_ff.3.weight",
      "multiview_ff.3.bias",
      "readout.0.weight",
      "readout.0.bias",
      "readout.1.weight",
      "readout.1.bias"
    ]
  }
}